telnet_proxy_server-0.1.0.dist-info/METADATA
telnet_proxy_server-0.1.0.dist-info/WHEEL
telnet_proxy_server-0.1.0.dist-info/entry_points.txt
telnet_proxy_server-0.1.0.dist-info/licenses/LICENSE.MD
telnet_proxy_server/__init__.py
telnet_proxy_server/config.yaml
telnet_proxy_server/proxy_handler.py
telnet_proxy_server/server.py
telnet_proxy_server-0.1.0.dist-info/RECORD
