Metadata-Version: 2.1
Name: telnet-proxy-server
Version: 0.1.0
Summary: WebSocket to Telnet proxy server that allows web clients to connect to Telnet servers
License: MIT
Project-URL: Homepage, https://github.com/chrishayuk/telnet-proxy-server
Project-URL: Issues, https://github.com/chrishayuk/telnet-proxy-server/issues
Requires-Python: >=3.11
Requires-Dist: asyncio>=3.4.3
Requires-Dist: chuk-protocol-server>=0.1.10
Requires-Dist: websockets>=15.0.1
